[
  {
    "_id": "ad0262db-6688-4604-bc3c-7200bc7bcab4",
    "tipo": "Sun Tunnels",
    "nome": "TGR 010",
    "quantidade": 0
  },
  {
    "_id": "a0b3f6f2-cc99-4e46-8f54-30052e1f6626",
    "tipo": "Sun Tunnels",
    "nome": "TMR 010",
    "quantidade": 0
  },
  {
    "_id": "9917eba5-a7e7-484d-82c2-ed337832fec9",
    "tipo": "Sun Tunnels",
    "nome": "THR 010",
    "quantidade": 0
  },
  {
    "_id": "f2dd74f2-8e8e-47f1-818a-27b2d6c852af",
    "tipo": "Sun Tunnels",
    "nome": "TGR 014",
    "quantidade": 0
  },
  {
    "_id": "dc5b2f3e-1152-46f8-9ac3-222f6422bc67",
    "tipo": "Sun Tunnels",
    "nome": "TMR 014",
    "quantidade": 0
  },
  {
    "_id": "da9ed056-c37c-44bd-a105-d92289f241be",
    "tipo": "Sun Tunnels",
    "nome": "TLR 014",
    "quantidade": 0
  },
  {
    "_id": "20407de2-de30-4d6f-809c-91114dd50573",
    "tipo": "Sun Tunnels",
    "nome": "TCR 014",
    "quantidade": 0
  },
  {
    "_id": "d025f242-7a6a-4dda-889a-52c13eea16fd",
    "tipo": "Sun Tunnels",
    "nome": "TCC 014",
    "quantidade": 0
  },
    {
      "_id": "7721cfd8-6b0a-4aa8-af04-0f06354f2a87",
      "tipo": "Sun Tunnels",
      "nome": "THR 014",
      "quantidade": 0
    },
    {
      "_id": "6f2210f7-dfa6-465a-ab11-a24e2e71d2cc",
      "tipo": "Sun Tunnels",
      "nome": "TGF 014",
      "quantidade": 0
    },
    {
      "_id": "6ebc9848-9d2b-4d59-a175-36c3fe32be8d",
      "tipo": "Sun Tunnels",
      "nome": "TMF 014",
      "quantidade": 0
    },
    {
      "_id": "a7cc78e6-2c3b-4998-9e9e-0aeca7c029c5",
      "tipo": "Sun Tunnels",
      "nome": "TGF 022",
      "quantidade": 0
    },
    {
      "_id": "2d733e73-117f-43c2-b2f3-2ff4b308569a",
      "tipo": "Sun Tunnels",
      "nome": "TGR 022",
      "quantidade": 0
    },
    {
      "_id": "1b8dcd97-e54e-4438-a43b-c7ebd4db6c33",
      "tipo": "Curb Mount",
      "nome": "FCM 1430 T",
      "quantidade": 0
    },
    {
      "_id": "6ab56594-c52c-4056-9876-cd87dbfab02a",
      "tipo": "Curb Mount",
      "nome": "FCM 1430 L",
      "quantidade": 0
    },
    {
      "_id": "6beb1d9d-0b9d-4766-bd19-41cc6314a566",
      "tipo": "Curb Mount",
      "nome": "FCM 1446 T",
      "quantidade": 0
    },
    {
      "_id": "00984ed7-3743-4abe-adfc-302aacca01f1",
      "tipo": "Curb Mount",
      "nome": "FCM 1446 L",
      "quantidade": 0
    },
    {
      "_id": "b3724b9a-a8fe-47db-8311-acdea96ea617",
      "tipo": "Curb Mount",
      "nome": "FCM 2222 T",
      "quantidade": 0
    },
    {
      "_id": "24f24ba8-1926-4dc2-ae58-9eb2ac7b323f",
      "tipo": "Curb Mount",
      "nome": "FCM 2222 L",
      "quantidade": 0
    },
    {
      "_id": "5f8d7957-9570-4548-af47-aedc7853dcdc",
      "tipo": "Curb Mount",
      "nome": "FCM 2222 WL",
      "quantidade": 0
    },
    {
      "_id": "a2fee7b9-7527-4228-bc48-d4ebcf282efb",
      "tipo": "Curb Mount",
      "nome": "FCM 2230 T",
      "quantidade": 0
    },
    {
      "_id": "01463116-3851-477d-8af9-e25f1ad63981",
      "tipo": "Curb Mount",
      "nome": "FCM 2230 L",
      "quantidade": 0
    },
    {
      "_id": "1d7a81aa-1976-4368-a56a-f4204e16e2ab",
      "tipo": "Curb Mount",
      "nome": "FCM 2234 T",
      "quantidade": 0
    },
    {
      "_id": "b343f656-8083-49be-ae3b-0d3cb266b1cd",
      "tipo": "Curb Mount",
      "nome": "FCM 2234 L",
      "quantidade": 0
    },
    {
      "_id": "e49c02ce-664f-43f6-a36e-eb1299451eb2",
      "tipo": "Curb Mount",
      "nome": "FCM 2246 T",
      "quantidade": 0
    },
    {
      "_id": "c11d3a5b-4e7e-4e25-b381-a065d7cbe469",
      "tipo": "Curb Mount",
      "nome": "FCM 2246 L",
      "quantidade": 0
    },
    {
      "_id": "561c289a-5329-46b0-8773-2d2319726ea9",
      "tipo": "Curb Mount",
      "nome": "FCM 2246 WL",
      "quantidade": 0
    },
    {
      "_id": "706ea45b-7ddb-4d97-85e0-a106625cec3d",
      "tipo": "Curb Mount",
      "nome": "FCM 2270 T",
      "quantidade": 0
    },
    {
      "_id": "9b324aa5-5876-4ae4-9000-ce1223c3b6dd",
      "tipo": "Curb Mount",
      "nome": "FCM 2270 L",
      "quantidade": 0
    },
    {
      "_id": "2b7cd138-2709-4878-8eb8-159f0d6f0c32",
      "tipo": "Curb Mount",
      "nome": "FCM 3030 T",
      "quantidade": 0
    },
    {
      "_id": "481bc2b9-508d-4af0-bb22-89c700e34077",
      "tipo": "Curb Mount",
      "nome": "FCM 3030 L",
      "quantidade": 0
    },
    {
      "_id": "8f6bf234-237d-4213-be9b-06647941c6fe",
      "tipo": "Curb Mount",
      "nome": "FCM 3046 T",
      "quantidade": 0
    },
    {
      "_id": "7fdb1ee2-5967-4cdc-9c08-9113687db668",
      "tipo": "Curb Mount",
      "nome": "FCM 3046 L",
      "quantidade": 0
    },
    {
      "_id": "548f3bfa-4cdd-45bf-af23-c7a56a61fce6",
      "tipo": "Curb Mount",
      "nome": "FCM 3055 L",
      "quantidade": 0
    },
    {
      "_id": "4f715ca6-328d-45e2-871a-e98620eace07",
      "tipo": "Curb Mount",
      "nome": "FCM 3434 T",
      "quantidade": 0
    },
    {
      "_id": "2fa90feb-8106-4d60-ac45-71d71809f244",
      "tipo": "Curb Mount",
      "nome": "FCM 3434 L",
      "quantidade": 0
    },
    {
      "_id": "6cf6f7b4-80ef-45bc-858d-a12d2b13697f",
      "tipo": "Curb Mount",
      "nome": "FCM 3446 T",
      "quantidade": 0
    },
    {
      "_id": "87539d47-0091-4d44-9c75-7e8057cd5de0",
      "tipo": "Curb Mount",
      "nome": "FCM 3446 L",
      "quantidade": 0
    },
    {
      "_id": "807703e7-4516-4cd6-85da-de85eb799669",
      "tipo": "Curb Mount",
      "nome": "FCM 4622 T",
      "quantidade": 0
    },
    {
      "_id": "cb486543-c001-4598-a056-d23873571017",
      "tipo": "Curb Mount",
      "nome": "FCM 4622 L",
      "quantidade": 0
    },
    {
      "_id": "b17137e4-5fc2-4a3d-9c34-c56ce05e9622",
      "tipo": "Curb Mount",
      "nome": "FCM 4646 T",
      "quantidade": 0
    },
    {
      "_id": "89637cb2-c1e9-43c8-9f57-f024c28e28f2",
      "tipo": "Curb Mount",
      "nome": "FCM 4646 L",
      "quantidade": 0
    },
    {
      "_id": "28ea6154-4b20-4dcc-9672-523ce1631e01",
      "tipo": "Curb Mount",
      "nome": "FCM 4672 L",
      "quantidade": 0
    },
    {
      "_id": "5785866f-0b62-4af1-a112-a00fd0e3eeeb",
      "tipo": "Acrylic Dome",
      "nome": "FX 2222",
      "quantidade": 0
    },
    {
      "_id": "8ab668a7-cbda-4152-b6ed-67070b360f13",
      "tipo": "Acrylic Dome",
      "nome": "FX 2246",
      "quantidade": 0
    },
    {
      "_id": "bf74409a-0cfe-4230-8028-b417e9d43f86",
      "tipo": "Acrylic Dome",
      "nome": "FX 3030",
      "quantidade": 0
    },
    {
      "_id": "3ecb866c-114d-48bc-b16c-d005550844c9",
      "tipo": "Acrylic Dome",
      "nome": "FX 3434",
      "quantidade": 0
    },
    {
      "_id": "02950e1a-ea11-4f29-827f-255bcc0b76bd",
      "tipo": "Acrylic Dome",
      "nome": "FX 4646",
      "quantidade": 0
    },
    {
      "_id": "638be0ec-885e-47d8-a190-9156d22fe816",
      "tipo": "Acrylic Dome",
      "nome": "FXG 225225 (2222)",
      "quantidade": 0
    },
    {
      "_id": "7e0dd93a-d7f6-49ea-a286-1932390b91ee",
      "tipo": "Acrylic Dome",
      "nome": "FXG 225465  (2246)",
      "quantidade": 0
    },
    {
      "_id": "2b207316-ffda-431a-947d-f1e684257368",
      "tipo": "Acrylic Dome",
      "nome": "FXG 345345 (3434)",
      "quantidade": 0
    },
    {
      "_id": "7ff03ff8-c5bc-4b2c-91c5-f4e430573ee4",
      "tipo": "Acrylic Dome",
      "nome": "FXG 465465 (4646)",
      "quantidade": 0
    },
    {
      "_id": "89d90d44-0429-462c-aed1-278be32c15c2",
      "tipo": "Curb-mount Flashing",
      "nome": "ECL 1446",
      "quantidade": 0
    },
    {
      "_id": "b0db6b22-e12e-4176-81de-4822594e227c",
      "tipo": "Curb-mount Flashing",
      "nome": "ECL 2246",
      "quantidade": 0
    },
    {
      "_id": "5ad0d234-0ac6-44b6-b2e7-b06f160fc65f",
      "tipo": "Curb-mount Flashing",
      "nome": "ECL 2270",
      "quantidade": 0
    },
    {
      "_id": "bae441c9-1302-4744-871d-b275515db3b2",
      "tipo": "Curb-mount Flashing",
      "nome": "ECL 3046",
      "quantidade": 0
    },
    {
      "_id": "b9ceb4a1-f138-4566-88e7-2ae5cdfcc045",
      "tipo": "Curb-mount Flashing",
      "nome": "ECL 3055",
      "quantidade": 0
    },
    {
      "_id": "1dcae39a-843f-48a3-8047-ed52c87a6762",
      "tipo": "Curb-mount Flashing",
      "nome": "ECL 3446",
      "quantidade": 0
    },
    {
      "_id": "dedb14fe-7b6e-46a3-bd1f-59cb9d5a1106",
      "tipo": "Curb-mount Flashing",
      "nome": "ECL 4646",
      "quantidade": 0
    },
    {
      "_id": "a476dad1-3d7e-427a-aeb3-fb5f549dbf4f",
      "tipo": "Curb-mount Flashing",
      "nome": "ECL 4672",
      "quantidade": 0
    },
    {
      "_id": "e014bb17-ca8a-4769-981f-5dee4b7c5f4c",
      "tipo": "Deck Mount",
      "nome": "VSS C01",
      "quantidade": 0
    },
    {
      "_id": "32bad240-dac0-417a-aa3f-d58bb359e4cd",
      "tipo": "Deck Mount",
      "nome": "VSS C04",
      "quantidade": 0
    },
    {
      "_id": "2344bddb-397b-4a3e-8f35-69bdb9366661",
      "tipo": "Deck Mount",
      "nome": "VSS C06",
      "quantidade": 0
    },
    {
      "_id": "73462077-552b-4520-98ca-6efa8bff7bb4",
      "tipo": "Deck Mount",
      "nome": "VSS C08",
      "quantidade": 0
    },
    {
      "_id": "01786213-2004-483f-ab92-00aa995c13f9",
      "tipo": "Deck Mount",
      "nome": "VSS M02",
      "quantidade": 0
    },
    {
      "_id": "6c3490bd-ab5d-4a63-9ae1-ab196f19f1cd",
      "tipo": "Deck Mount",
      "nome": "VSS M04",
      "quantidade": 0
    },
    {
      "_id": "1ad21a5c-dbef-4c56-b2c5-38e978739a44",
      "tipo": "Deck Mount",
      "nome": "VSS M06",
      "quantidade": 0
    },
    {
      "_id": "8113d553-75f5-4591-ab8a-75d17e9e9260",
      "tipo": "Deck Mount",
      "nome": "VSS M08",
      "quantidade": 0
    },
    {
      "_id": "5cbef705-529a-4f3c-95cf-4403e35df302",
      "tipo": "Deck Mount",
      "nome": "VSS S01",
      "quantidade": 0
    },
    {
      "_id": "de9bf8f9-6c41-471f-bc8b-b6ab4a20da7e",
      "tipo": "Deck Mount",
      "nome": "VSS S06",
      "quantidade": 0
    },
    {
      "_id": "76105acc-b1bd-448a-80df-32d10227e962",
      "tipo": "Deck Mount",
      "nome": "VS S06 (04D)",
      "quantidade": 0
    },
    {
      "_id": "d6c3a052-3d75-4384-9d28-0b148ed478f7",
      "tipo": "Deck Mount",
      "nome": "VCS 2222 (00W)",
      "quantidade": 0
    },
    {
      "_id": "4c456739-a1e4-4a6f-8741-f4727182d439",
      "tipo": "Deck Mount",
      "nome": "VCS 2234",
      "quantidade": 0
    },
    {
      "_id": "06ea88e2-7827-4d28-a43a-956098289eb2",
      "tipo": "Deck Mount",
      "nome": "VCS 2246 (004E)",
      "quantidade": 0
    },
    {
      "_id": "425aa3f2-0d63-4afe-8a4c-ea1f51ef7721",
      "tipo": "Deck Mount",
      "nome": "VCS 3046 (04E)",
      "quantidade": 0
    },
    {
      "_id": "cfbf4a53-7c20-468f-98e9-9bb27b167688",
      "tipo": "Deck Mount",
      "nome": "VCS 4622",
      "quantidade": 0
    },
    {
      "_id": "78423280-8e54-4e1c-a067-e52d54af3d51",
      "tipo": "Deck Mount",
      "nome": "VCS 4646",
      "quantidade": 0
    },
    {
      "_id": "d6f6fb09-432e-41f2-91e8-7ae9dbd9724c",
      "tipo": "Deck Mount",
      "nome": "VCS 2246CS00",
      "quantidade": 0
    },
    {
      "_id": "3b7f8514-5b26-4aae-a988-f8e0506e5ebb",
      "tipo": "Deck Mount",
      "nome": "VCS 2246 (04E)",
      "quantidade": 0
    },
    {
      "_id": "f4c8ff52-d202-41ac-b238-f26c49db9e1f",
      "tipo": "Deck Mount",
      "nome": "VS C04",
      "quantidade": 0
    },
    {
      "_id": "81041536-8b88-498a-91bb-5a91ea119621",
      "tipo": "Deck Mount",
      "nome": "VS C06",
      "quantidade": 0
    },
    {
      "_id": "211dc928-c0ec-454d-b1f7-7d0b8c391cba",
      "tipo": "Deck Mount",
      "nome": "VS C08",
      "quantidade": 0
    },
    {
      "_id": "86c6771a-530b-4e27-a2a8-568f817a88e1",
      "tipo": "Deck Mount",
      "nome": "VS M02",
      "quantidade": 0
    },
    {
      "_id": "22d86e96-b611-42b0-9a7e-9e4bcbe1621d",
      "tipo": "Deck Mount",
      "nome": "VS M04",
      "quantidade": 0
    },
    {
      "_id": "2d792b19-05ad-4955-9ede-8f548274abbe",
      "tipo": "Deck Mount",
      "nome": "VS M06",
      "quantidade": 0
    },
    {
      "_id": "3f721ac5-c4b5-4285-ae02-5840221b4604",
      "tipo": "Deck Mount",
      "nome": "VS M08",
      "quantidade": 0
    },
    {
      "_id": "d55dd714-c2e5-4510-b0cc-7b453416a98d",
      "tipo": "Deck Mount",
      "nome": "VS S01",
      "quantidade": 0
    },
    {
      "_id": "7f5a6b87-e2bc-4144-8e4b-0298c3540b82",
      "tipo": "Deck Mount",
      "nome": "VS S06",
      "quantidade": 0
    },
    {
      "_id": "bad85039-4a88-4def-b4f4-f168152d4c2b",
      "tipo": "Deck Mount",
      "nome": "VCE 3046",
      "quantidade": 0
    },
    {
      "_id": "520c38a6-7166-4f5f-bf94-8abd55e28165",
      "tipo": "Deck Mount",
      "nome": "VCE 2246",
      "quantidade": 0
    },
    {
      "_id": "7b3dd02a-a015-4817-ba8f-4f5ed9ef6a88",
      "tipo": "Deck Mount",
      "nome": "VCS 2234",
      "quantidade": 0
    },
    {
      "_id": "d4104756-1028-464b-be9f-4f47f8a2033c",
      "tipo": "Deck Mount",
      "nome": "VCS 3030",
      "quantidade": 0
    },
    {
      "_id": "2d67dbe4-3830-4d61-88b1-d270f0810e8d",
      "tipo": "Deck Mount",
      "nome": "VCS 3046",
      "quantidade": 0
    },
    {
      "_id": "7e879232-c9b3-479c-9edf-0f12b079eb4c",
      "tipo": "Deck Mount",
      "nome": "VCS 3434",
      "quantidade": 0
    },
    {
      "_id": "fc318357-994f-4c23-9b58-0b1cea60271d",
      "tipo": "Deck Mount",
      "nome": "VCS 4622",
      "quantidade": 0
    },
    {
      "_id": "301b3063-23f7-486a-920e-85f856bc527f",
      "tipo": "Deck Mount",
      "nome": "VCS 4646 (",
      "quantidade": 0
    },
    {
      "_id": "8f7db202-ad8c-4f8e-9edc-177a1eb2f6a4",
      "tipo": "Deck Mount",
      "nome": "VCS 2246CS00",
      "quantidade": 0
    },
    {
      "_id": "6f59efd0-5981-4e8b-b2f6-dc88457fa531",
      "tipo": "Deck Mount",
      "nome": "VCS 2246 (04E)",
      "quantidade": 0
    },
    {
      "_id": "f0335220-5ad7-4aae-a9f5-fced2f03e678",
      "tipo": "Deck Mount",
      "nome": "VSS C06",
      "quantidade": 0
    },
    {
      "_id": "3c5aced6-dc6b-4a80-92ff-b732e12ed50d",
      "tipo": "Deck Mount",
      "nome": "VSE C01",
      "quantidade": 0
    },
    {
      "_id": "04b807e6-e72b-4a62-963b-a825b9310734",
      "tipo": "Deck Mount",
      "nome": "VCM 2222 T",
      "quantidade": 0
    },
    {
      "_id": "9452c12a-b00c-43c3-8b69-f0f02d6a8d85",
      "tipo": "Deck Mount",
      "nome": "VCM 2222 L",
      "quantidade": 0
    },
    {
      "_id": "b1308e1b-0b8e-4bf6-adcc-3ac74576d9ea",
      "tipo": "Deck Mount",
      "nome": "VCM 2234 T",
      "quantidade": 0
    },
    {
      "_id": "17b345bd-2294-4af4-a08f-3fac4e8ceb5f",
      "tipo": "Deck Mount",
      "nome": "VCM 2234 L",
      "quantidade": 0
    },
    {
      "_id": "8869bab3-ee1b-4a9c-901a-9337dea0b70a",
      "tipo": "Deck Mount",
      "nome": "VCM 2246 L 00W",
      "quantidade": 0
    },
    {
      "_id": "d9de9765-5386-4389-be01-a735b9061b6e",
      "tipo": "Deck Mount",
      "nome": "VCM 2246 L",
      "quantidade": 0
    },
    {
      "_id": "f16260a1-7e0f-489d-a4bb-220d9410a07d",
      "tipo": "Deck Mount",
      "nome": "VCM 3030 T",
      "quantidade": 0
    },
    {
      "_id": "05d41240-5959-4bd0-8644-91c58fceaf58",
      "tipo": "Deck Mount",
      "nome": "VCM 3030 L",
      "quantidade": 0
    },
    {
      "_id": "68f467c8-068f-4505-ab1d-fe3de438bb12",
      "tipo": "Deck Mount",
      "nome": "VCM 3046 T",
      "quantidade": 0
    },
    {
      "_id": "0f9899ce-a6a6-4cf1-8e7a-f5ef52a62f13",
      "tipo": "Deck Mount",
      "nome": "VCM 3046 L",
      "quantidade": 0
    },
    {
      "_id": "8633990c-51c7-4dda-bb37-f8edf628d4b0",
      "tipo": "Deck Mount",
      "nome": "VCM 3434 T",
      "quantidade": 0
    },
    {
      "_id": "7561a947-16ca-42c0-ba4a-9a4cc3426a56",
      "tipo": "Deck Mount",
      "nome": "VCM 3434 L",
      "quantidade": 0
    },
    {
      "_id": "63bf1ca3-34a5-4c2c-8dd5-fec8c81795be",
      "tipo": "Deck Mount",
      "nome": "VCM 4646 T",
      "quantidade": 0
    },
    {
      "_id": "59a6ddeb-084c-4dea-b3e2-5969b78c55c2",
      "tipo": "Deck Mount",
      "nome": "VCM 4646 L",
      "quantidade": 0
    },
    {
      "_id": "776f0d81-0e30-4f80-83fb-3d568f5fa000",
      "tipo": "Deck Mount",
      "nome": "FS A06 (00W)",
      "quantidade": 0
    },
    {
      "_id": "4a02632a-dd0c-4bea-9ec2-ce25f5554371",
      "tipo": "Deck Mount",
      "nome": "FS A06",
      "quantidade": 0
    },
    {
      "_id": "f4e2fffb-f6eb-4691-9cdf-df45d69c374b",
      "tipo": "Deck Mount",
      "nome": "FS C01",
      "quantidade": 0
    },
    {
      "_id": "a6fc94c2-f2c5-45c8-94b6-a7909e5629f6",
      "tipo": "Deck Mount",
      "nome": "FS C04",
      "quantidade": 0
    },
    {
      "_id": "0724dabc-ce9c-465a-83aa-a17a06ad1440",
      "tipo": "Deck Mount",
      "nome": "FS C06",
      "quantidade": 0
    },
    {
      "_id": "0add6260-d5b1-4acb-9fd5-498989236b00",
      "tipo": "Deck Mount",
      "nome": "FS C06PA00",
      "quantidade": 0
    },
    {
      "_id": "f2c9c0ab-b33a-4c8b-a6c3-46ca9f97ef54",
      "tipo": "Deck Mount",
      "nome": "FS C08",
      "quantidade": 0
    },
    {
      "_id": "eccc23db-adb5-483e-b62a-e4eedca38175",
      "tipo": "Deck Mount",
      "nome": "FS C08CS00",
      "quantidade": 0
    },
    {
      "_id": "b34a2c85-5273-46e4-b3b9-acfbf0483a5b",
      "tipo": "Deck Mount",
      "nome": "FS C12",
      "quantidade": 0
    },
    {
      "_id": "a1fd440b-5528-447c-a932-99886ace3de3",
      "tipo": "Deck Mount",
      "nome": "FS D06",
      "quantidade": 0
    },
    {
      "_id": "57a412dc-4b3f-4437-bf73-8e37e7bb8704",
      "tipo": "Deck Mount",
      "nome": "FS D26",
      "quantidade": 0
    },
    {
      "_id": "b1097803-3081-4624-b872-23571db14b90",
      "tipo": "Deck Mount",
      "nome": "FS M02",
      "quantidade": 0
    },
    {
      "_id": "4209e777-936c-4608-8a39-c186a5b024fc",
      "tipo": "Deck Mount",
      "nome": "FS M04",
      "quantidade": 0
    },
    {
      "_id": "3fd97c4f-6531-4a60-8806-9717fa9b29d2",
      "tipo": "Deck Mount",
      "nome": "FS M06",
      "quantidade": 0
    },
    {
      "_id": "c155ef48-4cdb-443d-a7b9-e84347251b77",
      "tipo": "Deck Mount",
      "nome": "FS M08",
      "quantidade": 0
    },
    {
      "_id": "8b0a0942-5968-4c28-9146-9ff150df6e69",
      "tipo": "Deck Mount",
      "nome": "FS M08CS00",
      "quantidade": 0
    },
    {
      "_id": "66b957df-a92b-4aee-a829-7b4e2e9eaec2",
      "tipo": "Deck Mount",
      "nome": "FS S01",
      "quantidade": 0
    },
    {
      "_id": "d7a057e8-d22b-49d8-b119-632c636e0697",
      "tipo": "Deck Mount",
      "nome": "FS S06 T",
      "quantidade": 0
    },
    {
      "_id": "fed403b7-08d6-49fe-b2f5-7b706a7dcf8a",
      "tipo": "Deck Mount",
      "nome": "FS S06 L",
      "quantidade": 0
    },
    {
      "_id": "2c737363-257d-4c48-9e8f-3403ba9f7f7f",
      "tipo": "Deck Mount",
      "nome": "FS S06 CS01XW",
      "quantidade": 0
    },
    {
      "_id": "d6de8f70-a9b9-4fa3-90e8-a912452c15c9",
      "tipo": "Deck Mount",
      "nome": "FSR M02",
      "quantidade": 0
    },
    {
      "_id": "7d2eff1e-b7fb-4965-933d-d4c3c6ec5515",
      "tipo": "Deck Mount",
      "nome": "GPU MK08",
      "quantidade": 0
    },
    {
      "_id": "1afc3694-7fc5-4891-88d1-309fd913ed40",
      "tipo": "Deck Mount",
      "nome": "GPU SK06",
      "quantidade": 0
    },
    {
      "_id": "594812ff-f3fb-498c-a81d-8dfa6487f513",
      "tipo": "Deck Mount",
      "nome": "EDL M08",
      "quantidade": 0
    },
    {
      "_id": "66ca4aec-7bd2-44c5-afef-61437501b05d",
      "tipo": "Deck Mount",
      "nome": "EDM C01",
      "quantidade": 0
    },
    {
      "_id": "a956b8b8-248f-4fd6-86ca-e2069b47eb97",
      "tipo": "Deck-mount Flashing",
      "nome": "EDL A06",
      "quantidade": 0
    },
    {
      "_id": "8bb08734-0a84-4734-b02c-8200dda0ab3f",
      "tipo": "Deck-mount Flashing",
      "nome": "EDL 056",
      "quantidade": 0
    },
    {
      "_id": "b4dcf0f5-5992-453b-8677-d1ea07815f2c",
      "tipo": "Deck-mount Flashing",
      "nome": "EDL 106",
      "quantidade": 0
    },
    {
      "_id": "1cb3dbd6-5cb6-4c51-a9bd-91330f65bbfd",
      "tipo": "Deck-mount Flashing",
      "nome": "EDL 112",
      "quantidade": 0
    },
    {
      "_id": "383656c0-e277-4db5-8cff-9b199d91a58b",
      "tipo": "Deck-mount Flashing",
      "nome": "EDL 156",
      "quantidade": 0
    },
    {
      "_id": "c85f5912-1ab9-465b-8313-c81f3db6a793",
      "tipo": "Deck-mount Flashing",
      "nome": "EDL C06",
      "quantidade": 0
    },
    {
      "_id": "470b491e-75fc-476b-ad34-e175d2d86f8c",
      "tipo": "Deck-mount Flashing",
      "nome": "EDL C12",
      "quantidade": 0
    },
    {
      "_id": "1c7a0cf4-9cba-42b7-bb81-6ec10b4544c5",
      "tipo": "Deck-mount Flashing",
      "nome": "EDL D06",
      "quantidade": 0
    },
    {
      "_id": "1340dcc8-d129-4167-aa3e-5e4c1e9e31a4",
      "tipo": "Deck-mount Flashing",
      "nome": "EDL SK06",
      "quantidade": 0
    },
    {
      "_id": "264b9002-36a4-45f9-9302-2dcb10f03d9c",
      "tipo": "Deck-mount Flashing",
      "nome": "EDW D06",
      "quantidade": 0
    },
    {
      "_id": "94732408-5ae9-4051-9087-5c36846f6166",
      "tipo": "Deck-mount Flashing",
      "nome": "EDM D06",
      "quantidade": 0
    },
    {
      "_id": "25e88725-887a-466e-bff4-3d02a2e2fe70",
      "tipo": "Deck-mount Flashing",
      "nome": "EDM D26",
      "quantidade": 0
    },
    {
      "_id": "5222a066-1b16-40ce-b733-9f7f2a3c7adb",
      "tipo": "Deck-mount Flashing",
      "nome": "EDL M08",
      "quantidade": 0
    },
    {
      "_id": "1180cbd6-76ea-4738-9eff-8019e779a07d",
      "tipo": "Deck-mount Flashing",
      "nome": "EDL 308",
      "quantidade": 0
    },
    {
      "_id": "b2cb2d01-afca-49ba-a71e-69542607083b",
      "tipo": "Deck-mount Flashing",
      "nome": "EDM M08",
      "quantidade": 0
    },
    {
      "_id": "1e27d2c8-c1b6-4419-bb1f-01ea8f470a22",
      "tipo": "Deck-mount Flashing",
      "nome": "EDL 606",
      "quantidade": 0
    },
    {
      "_id": "c1ea5e54-c232-4a89-b7b7-2a86613b072b",
      "tipo": "Deck-mount Flashing",
      "nome": "EDL S06",
      "quantidade": 0
    },
    {
      "_id": "413035a9-fda0-4255-a6c8-c237996a2759",
      "tipo": "Deck-mount Flashing",
      "nome": "EDM S06",
      "quantidade": 0
    },
    {
      "_id": "a565d332-075c-4f22-b02c-589cc84fa7de",
      "tipo": "Deck-mount Flashing",
      "nome": "ECW 2270",
      "quantidade": 0
    },
    {
      "_id": "301339ab-f0ff-4f7e-8c4d-0c565e908de3",
      "tipo": "Self-Flashed",
      "nome": "QPF 2222",
      "quantidade": 0
    },
    {
      "_id": "e2d5d7b3-2e4c-4b84-b2e6-715fd95c9992",
      "tipo": "Self-Flashed",
      "nome": "QPF 2246",
      "quantidade": 0
    },
    {
      "_id": "1e85b2c2-2e81-4fac-b9e5-19ed7bd965dd",
      "tipo": "Self-Flashed",
      "nome": "QPF 3046",
      "quantidade": 0
    },
    {
      "_id": "0956cfe9-a348-4f7f-87c4-ef1608a6210b",
      "tipo": "Self-Flashed",
      "nome": "QX 2222",
      "quantidade": 0
    },
    {
      "_id": "bdbdf7d1-154e-4cfd-8fd9-f3edc71e87dc",
      "tipo": "Self-Flashed",
      "nome": "QX 2246",
      "quantidade": 0
    }
  ]